uspec_finder/__init__.py
uspec_finder/config.py
uspec_finder/finding_chart.py
uspec_finder/shapes.py
uspec_finder/skyview.py
uspec_finder/uspec.py
uspec_finder/uspec_finder.py
uspec_finder/data/Lato-Black.ttf
uspec_finder/data/Lato-Regular.ttf
uspec_finder/data/README.rst
uspec_finder/data/config
uspec_finder/data/configspec.ini
uspec_finder-1.0.3.data/scripts/usfinder
uspec_finder-1.0.3.dist-info/AUTHORS.rst
uspec_finder-1.0.3.dist-info/LICENSE
uspec_finder-1.0.3.dist-info/METADATA
uspec_finder-1.0.3.dist-info/WHEEL
uspec_finder-1.0.3.dist-info/top_level.txt
uspec_finder-1.0.3.dist-info/RECORD
