Metadata-Version: 2.1
Name: uspec-finder
Version: 1.0.3
Summary: Observation planning and finding charts for HiPerCAM
Home-page: https://github.com/HiPERCAM/uspec_finder
Author: Stuart Littlefair
Author-email: s.littlefair@shef.ac.uk
License: MIT license
Download-URL: https://github.com/HiPERCAM/uspec_finder/archive/v1.0.3.tar.gz
Keywords: uspec_finder
Platform: UNKNOWN
Classifier: Development Status :: 2 - Pre-Alpha
Classifier: Intended Audience :: Developers
Classifier: License :: OSI Approved :: MIT License
Classifier: Natural Language :: English
Classifier: Programming Language :: Python :: 2
Classifier: Programming Language :: Python :: 2.6
Classifier: Programming Language :: Python :: 2.7
Classifier: Programming Language :: Python :: 3
Classifier: Programming Language :: Python :: 3.3
Classifier: Programming Language :: Python :: 3.4
Classifier: Programming Language :: Python :: 3.5
Requires-Dist: ginga
Requires-Dist: astropy
Requires-Dist: pillow
Requires-Dist: configobj
Requires-Dist: hcam-widgets (>=0.7.3)
